Metadata-Version: 2.1
Name: bitfinex-v2-proxy
Version: 1.8.1
Summary: Python client for the Bitfinex API
Home-page: https://github.com/ohenrik/bitfinex
Author: Ole Henrik Skogstrøm
Author-email: henrik@amplify.no
License: MIT
Keywords: bitcoin,btc
Platform: UNKNOWN
License-File: LICENSE.md
